{
  "273656279": {
    "chat_id": 273656279,
    "username": "ursvlad",
    "first_name": "Влад",
    "active": true,
    "monitoring": true,
    "registered_at": "2026-05-08T22:36:14.701985",
    "last_seen": "2026-07-02T15:11:27.726865",
    "buy_threshold": 44.65,
    "sell_threshold": 46.8,
    "min_amount_uah": 10000,
    "min_amount_sell": 20000,
    "check_interval": 20,
    "balance_usdt": 0.0,
    "blacklist_buy": [],
    "blacklist_sell": [],
    "sell_card_threshold": 44.6,
    "blacklist_sell_card": [
      "USDTselleer",
      "Emmamur26_",
      "No_Back",
      "VIP_ObMinn",
      "CashQuick",
      "6O6",
      "pereborr",
      "P2p0bmIn",
      "1GRIVNAbro",
      "_Kolomoisky_"
    ],
    "enabled_exchanges": [
      "bybit",
      "binance"
    ],
    "cross_spread_min": 1.0,
    "bybit_buy_threshold": 41.0,
    "bybit_sell_threshold": 45.3,
    "whitelist_buy": [],
    "whitelist_sell": []
  },
  "6477920477": {
    "chat_id": 6477920477,
    "username": "vadim_emetc",
    "first_name": "Вадим",
    "active": false,
    "monitoring": true,
    "registered_at": "2026-05-08T22:38:15.944376",
    "last_seen": "2026-05-08T22:39:41.867985",
    "buy_threshold": 45.0,
    "sell_threshold": 45.9,
    "min_amount_uah": 2000,
    "min_amount_sell": 20000,
    "check_interval": 20,
    "balance_usdt": 0.0,
    "blacklist_buy": [],
    "blacklist_sell": []
  },
  "573540302": {
    "chat_id": 573540302,
    "username": "emchenkoss",
    "first_name": "emchenkoss",
    "active": true,
    "monitoring": true,
    "registered_at": "2026-05-08T22:41:24.872094",
    "last_seen": "2026-06-01T15:08:09.191653",
    "buy_threshold": 44.0,
    "sell_threshold": 46.5,
    "min_amount_uah": 70989898676,
    "min_amount_sell": 20000,
    "check_interval": 20,
    "balance_usdt": 1200.0,
    "blacklist_buy": [],
    "blacklist_sell": [
      "richpiana"
    ]
  },
  "848630979": {
    "chat_id": 848630979,
    "username": "qwoolexx",
    "first_name": "Ярик",
    "active": true,
    "monitoring": false,
    "registered_at": "2026-05-08T23:28:34.671922",
    "last_seen": "2026-05-09T15:15:36.327884",
    "buy_threshold": 43.8,
    "sell_threshold": 45.9,
    "min_amount_uah": 3000,
    "min_amount_sell": 50000,
    "check_interval": 20,
    "balance_usdt": 0.0,
    "blacklist_buy": [],
    "blacklist_sell": []
  }
}